{
  "main": {
    "id": "1cca669eb176dfc2",
    "type": "split",
    "children": [
      {
        "id": "b0485da6809d8818",
        "type": "tabs",
        "children": [
          {
            "id": "efa24cc8115bfd80",
            "type": "leaf",
            "state": {
              "type": "markdown",
              "state": {
                "file": "Natural Laws/Kianemos.md",
                "mode": "source",
                "source": false
              },
              "icon": "lucide-file",
              "title": "Kianemos"
            }
          }
        ]
      }
    ],
    "direction": "vertical"
  },
  "left": {
    "id": "f06e8af55fd1a7fd",
    "type": "split",
    "children": [
      {
        "id": "06ea144c6f8c5a4b",
        "type": "tabs",
        "children": [
          {
            "id": "112e531152fced58",
            "type": "leaf",
            "state": {
              "type": "file-explorer",
              "state": {
                "sortOrder": "alphabetical",
                "autoReveal": false
              },
              "icon": "lucide-folder-closed",
              "title": "Files"
            }
          },
          {
            "id": "ae099dd399c7de06",
            "type": "leaf",
            "state": {
              "type": "search",
              "state": {
                "query": "",
                "matchingCase": false,
                "explainSearch": false,
                "collapseAll": false,
                "extraContext": false,
                "sortOrder": "alphabetical"
              },
              "icon": "lucide-search",
              "title": "Search"
            }
          },
          {
            "id": "bedeb34170df996f",
            "type": "leaf",
            "state": {
              "type": "bookmarks",
              "state": {},
              "icon": "lucide-bookmark",
              "title": "Bookmarks"
            }
          }
        ]
      }
    ],
    "direction": "horizontal",
    "width": 300
  },
  "right": {
    "id": "f2cbf378861b6acc",
    "type": "split",
    "children": [
      {
        "id": "aaf273f1950bc4fc",
        "type": "tabs",
        "children": [
          {
            "id": "aef5f48aefe3f2c1",
            "type": "leaf",
            "state": {
              "type": "backlink",
              "state": {
                "file": "Welcome.md",
                "collapseAll": false,
                "extraContext": false,
                "sortOrder": "alphabetical",
                "showSearch": false,
                "searchQuery": "",
                "backlinkCollapsed": false,
                "unlinkedCollapsed": true
              },
              "icon": "links-coming-in",
              "title": "Backlinks for Welcome"
            }
          },
          {
            "id": "2535135fd1b80135",
            "type": "leaf",
            "state": {
              "type": "outgoing-link",
              "state": {
                "file": "Welcome.md",
                "linksCollapsed": false,
                "unlinkedCollapsed": true
              },
              "icon": "links-going-out",
              "title": "Outgoing links from Welcome"
            }
          },
          {
            "id": "f24d100e34a44810",
            "type": "leaf",
            "state": {
              "type": "tag",
              "state": {
                "sortOrder": "frequency",
                "useHierarchy": true,
                "showSearch": false,
                "searchQuery": ""
              },
              "icon": "lucide-tags",
              "title": "Tags"
            }
          },
          {
            "id": "831b96f4da8b1b26",
            "type": "leaf",
            "state": {
              "type": "outline",
              "state": {
                "file": "Welcome.md",
                "followCursor": false,
                "showSearch": false,
                "searchQuery": ""
              },
              "icon": "lucide-list",
              "title": "Outline of Welcome"
            }
          }
        ]
      }
    ],
    "direction": "horizontal",
    "width": 300,
    "collapsed": true
  },
  "left-ribbon": {
    "hiddenItems": {
      "switcher:Open quick switcher": false,
      "graph:Open graph view": false,
      "canvas:Create new canvas": false,
      "daily-notes:Open today's daily note": false,
      "templates:Insert template": false,
      "command-palette:Open command palette": false
    }
  },
  "active": "efa24cc8115bfd80",
  "lastOpenFiles": [
    "Natural Laws/Kianemos.md",
    "Pasted image 20250503152437.png",
    "Fauna & Flora/Petoudaima - Blood Butterfly.md",
    "pictures/Untitled.md",
    "pictures",
    "Fauna & Flora/Unicorns.md",
    "Fauna & Flora/Caverns.md",
    "Realms/Pirusia.md",
    "Fauna & Flora/Paraskanos - Blue Wings.md",
    "History & Mythology/The Primordial Wars.md",
    "History & Mythology/The Forgotten Age of Gods.md",
    "History & Mythology/Founding of Kheiossand.md",
    "History & Mythology/Demigods.md",
    "History & Mythology/Age of Strife - Age of Heroes.md",
    "Races/Primordials.md",
    "Kheiossand/Cavern layer.md",
    "Cities/City of Loshk.md",
    "Cities/City of Thelspri.md",
    "Realms/Land of the Bakaur.md",
    "Realms/Hidden Kingdom.md",
    "Realms/Grüdsandt.md",
    "Realms/Bagriian.md",
    "Realms/Aupuni Nalu.md",
    "NPCs/The Palaima Family.md",
    "Kheiossand/800 year anniversary.md",
    "Realms/Kheiossand.md",
    "Races/Bakaur.md",
    "Untitled.canvas",
    "Organisations",
    "Untitled 1.canvas",
    "Kheioi/Untitled",
    "NPCs",
    "Natural Laws",
    "Kheiossand",
    "Cities",
    "Fauna & Flora",
    "History & Mythology",
    "Realms"
  ]
}